lihash/__init__.py
lihash/src/functions.py
mhash/__init__.py
mhash/src/functions.py
lihash-1.0.2.dist-info/LICENSE
lihash-1.0.2.dist-info/METADATA
lihash-1.0.2.dist-info/WHEEL
lihash-1.0.2.dist-info/top_level.txt
lihash-1.0.2.dist-info/RECORD
