Metadata-Version: 2.1
Name: lihash
Version: 1.0.2
Summary: hashing strings
Author: Moses Dastmard
License-File: LICENSE
